README.txt
ip_address.py
setup.py
MazIPAddress.egg-info/PKG-INFO
MazIPAddress.egg-info/SOURCES.txt
MazIPAddress.egg-info/dependency_links.txt
MazIPAddress.egg-info/top_level.txt